{
    "type": "FeatureCollection",
    "features": [
      {
        "type": "Feature",
        "properties": {},
        "geometry": {
          "coordinates": [
            [
              [
                -78.90464628222658,
                43.497456796530884
              ],
              [
                -78.90464628222658,
                37.656846336987755
              ],
              [
                -68.48658755741297,
                37.656846336987755
              ],
              [
                -68.48658755741297,
                43.497456796530884
              ],
              [
                -78.90464628222658,
                43.497456796530884
              ]
            ]
          ],
          "type": "Polygon"
        }
      }
    ]
  }